retryz/__init__.py
retryz/__init__.pyc
retryz-0.1.9.dist-info/DESCRIPTION.rst
retryz-0.1.9.dist-info/METADATA
retryz-0.1.9.dist-info/RECORD
retryz-0.1.9.dist-info/WHEEL
retryz-0.1.9.dist-info/metadata.json
retryz-0.1.9.dist-info/pbr.json
retryz-0.1.9.dist-info/top_level.txt
