Metadata-Version: 2.0
Name: retryz
Version: 0.1.9
Summary: Retry decorator with a bunch of configuration parameters.
Home-page: http://github.com/jealous/retryz
Author: Cedric Zhuang
Author-email: jealous@163.com
License: Apache Software License
Keywords: retry decorator
Platform: any
Classifier: Programming Language :: Python
Classifier: Programming Language :: Python :: 2.7
Classifier: Programming Language :: Python :: 3.4
Classifier: Programming Language :: Python :: 3.5
Classifier: Programming Language :: Python :: 3.6
Classifier: Programming Language :: Python :: Implementation :: CPython
Classifier: Programming Language :: Python :: Implementation :: PyPy
Classifier: Natural Language :: English
Classifier: Intended Audience :: Developers
Classifier: Operating System :: OS Independent
Classifier: Development Status :: 5 - Production/Stable
Classifier: Topic :: Utilities
Classifier: License :: OSI Approved :: Apache Software License
